sea/__init__.py
sea/_version.py
sea/app.py
sea/cli.py
sea/cmds.py
sea/config.py
sea/datatypes.py
sea/exceptions.py
sea/format.py
sea/local.py
sea/middleware.py
sea/servicer.py
sea/signals.py
sea/utils.py
sea/contrib/extensions/__init__.py
sea/contrib/extensions/sentry.py
sea/contrib/extensions/celery/__init__.py
sea/contrib/extensions/celery/cmd.py
sea/contrib/extensions/celery/empty_celeryapp.py
sea/pb2/__init__.py
sea/pb2/default.proto
sea/pb2/default_pb2.py
sea/server/__init__.py
sea/server/multiprocessing.py
sea/server/threading.py
sea/template/.coveragerc
sea/template/.gitignore
sea/template/pytest.ini
sea/template/requirements.txt.tmpl
sea/template/test-requirements.txt
sea/template/app/__init__.py.tmpl
sea/template/app/async_tasks.py.tmpl
sea/template/app/buses.py.tmpl
sea/template/app/extensions.py.tmpl
sea/template/app/models.py.tmpl
sea/template/app/servicers.py.tmpl
sea/template/configs/__init__.py.tmpl
sea/template/configs/development.py.tmpl
sea/template/configs/production.py.tmpl
sea/template/configs/testing.py.tmpl
sea/template/configs/default/__init__.py.tmpl
sea/template/configs/default/async_task.py.tmpl
sea/template/configs/default/bus.py.tmpl
sea/template/configs/default/cache.py.tmpl
sea/template/configs/default/peewee.py.tmpl
sea/template/jobs/__init__.py.tmpl
sea/template/protos/.keep
sea/template/tests/__init__.py.tmpl
sea/template/tests/conftest.py.tmpl
sea/test/__init__.py
sea/test/fixtures.py
sea/test/stub.py
sea-4.0.0.dist-info/licenses/LICENSE
tests/test_contrib/__init__.py
tests/test_contrib/test_extensions/__init__.py
tests/test_contrib/test_extensions/test_celery.py
sea-4.0.0.dist-info/METADATA
sea-4.0.0.dist-info/WHEEL
sea-4.0.0.dist-info/entry_points.txt
sea-4.0.0.dist-info/top_level.txt
sea-4.0.0.dist-info/RECORD
