Metadata-Version: 2.4
Name: sea
Version: 4.0.0
Summary: shanbay rpc framework
Home-page: https://github.com/shanbay/sea
Author: Michael Ding
Author-email: yandy.ding@gmail.com
License: MIT
Keywords: rpc,grpc
Classifier: Development Status :: 5 - Production/Stable
Classifier: Environment :: Web Environment
Classifier: Intended Audience :: Developers
Classifier: Operating System :: POSIX
Classifier: License :: OSI Approved :: MIT License
Classifier: Programming Language :: Python
Classifier: Programming Language :: Python :: 3
Classifier: Programming Language :: Python :: 3.8
Classifier: Programming Language :: Python :: 3.9
Classifier: Programming Language :: Python :: 3.10
Classifier: Topic :: Internet
Classifier: Topic :: Software Development :: Libraries :: Python Modules
Requires-Python: >=3
License-File: LICENSE
Requires-Dist: grpcio<1.69.0,>=1.49.0
Requires-Dist: grpcio-tools<1.69.0,>=1.49.0
Requires-Dist: grpcio-reflection
Requires-Dist: protobuf<=6.31.1
Requires-Dist: pendulum
Requires-Dist: blinker<=1.8.2
Requires-Dist: jinja2==3.1.2
Requires-Dist: markupsafe
Dynamic: author
Dynamic: author-email
Dynamic: classifier
Dynamic: description
Dynamic: description-content-type
Dynamic: home-page
Dynamic: keywords
Dynamic: license
Dynamic: license-file
Dynamic: requires-dist
Dynamic: requires-python
Dynamic: summary
